easy_fir_filter/__init__.py
easy_fir_filter/easy_fir_filter.py
easy_fir_filter/exceptions/__init__.py
easy_fir_filter/exceptions/filter_conf_exceptions.py
easy_fir_filter/factory/__init__.py
easy_fir_filter/factory/filter_factory.py
easy_fir_filter/filters/__init__.py
easy_fir_filter/filters/bandpass_filter.py
easy_fir_filter/filters/bandstop_filter.py
easy_fir_filter/filters/highpass_filter.py
easy_fir_filter/filters/lowpass_filter.py
easy_fir_filter/interfaces/__init__.py
easy_fir_filter/interfaces/easy_fir_filter_interface.py
easy_fir_filter/interfaces/filter_interface.py
easy_fir_filter/interfaces/window_interface.py
easy_fir_filter/types/__init__.py
easy_fir_filter/types/fir_filter_conf.py
easy_fir_filter/utils/__init__.py
easy_fir_filter/utils/build_filter_coefficients.py
easy_fir_filter/utils/table.py
easy_fir_filter/utils/truncate.py
easy_fir_filter/validators/__init__.py
easy_fir_filter/validators/_filter_conf_type_validator.py
easy_fir_filter/validators/_filter_conf_values_validator.py
easy_fir_filter/validators/filter_conf_validator.py
easy_fir_filter/windows/__init__.py
easy_fir_filter/windows/blackman_window.py
easy_fir_filter/windows/hamming_window.py
easy_fir_filter/windows/kaiser_window.py
easy_fir_filter-0.1.0.dist-info/METADATA
easy_fir_filter-0.1.0.dist-info/WHEEL
easy_fir_filter-0.1.0.dist-info/entry_points.txt
easy_fir_filter-0.1.0.dist-info/licenses/LICENSE
easy_fir_filter-0.1.0.dist-info/RECORD
