Metadata-Version: 2.4
Name: easy-fir-filter
Version: 0.1.0
Summary: A simple python package to design and apply FIR filters.
Author-email: Guillermo Valverde <guillermovalverde@gmail.com>
Maintainer-email: Guillermo Valverde <guillermovalverde@gmail.com>
License: MIT License
License-File: LICENSE
Keywords: DSP,FIR,digital signal processing,filter,signals
Classifier: Development Status :: 4 - Beta
Classifier: Intended Audience :: Developers
Classifier: Intended Audience :: Science/Research
Classifier: License :: OSI Approved :: MIT License
Classifier: Programming Language :: Python :: 3
Classifier: Programming Language :: Python :: 3.12
Classifier: Topic :: Scientific/Engineering
Requires-Python: >=3.10
Requires-Dist: matplotlib>=3.10.0
Requires-Dist: numpy>=2.2.2
Requires-Dist: scipy>=1.15.1
Requires-Dist: tabulate>=0.9.0
